hqc/__init__.py
hqc/hqc.py
hqc/version.py
hqc/tests/__init__.py
hqc/tests/test_common.py
hqc/tests/test_hqc.py
hqc/tests/test_template.py
hqc-0.1.4.dist-info/LICENSE.txt
hqc-0.1.4.dist-info/METADATA
hqc-0.1.4.dist-info/WHEEL
hqc-0.1.4.dist-info/top_level.txt
hqc-0.1.4.dist-info/RECORD
