Metadata-Version: 2.1
Name: hqc
Version: 0.1.4
Summary: A package for the Helstrom Quantum Centroid classifier
Home-page: https://github.com/leockl/helstrom-quantum-centroid-classifier
Author: Leo Chow, Giuseppe Sergioli, Roberto Giuntini.
Author-email: leo.chow11@gmail.com
License: UNKNOWN
Platform: UNKNOWN
Classifier: Programming Language :: Python :: 3
Classifier: License :: OSI Approved :: BSD License
Classifier: Operating System :: OS Independent
Requires-Python: >=3.6
Requires-Dist: numpy
Requires-Dist: scipy
Requires-Dist: scikit-learn
Requires-Dist: joblib
Requires-Dist: sphinx
Requires-Dist: sphinx-gallery
Requires-Dist: sphinx-rtd-theme
